<?xml version="1.0" encoding="UTF-8"?>
<beans xmlns="http://www.springframework.org/schema/beans"
        xmlns:xsi="http://www.w3.org/2001/XMLSchema-instance"
        xsi:schemaLocation="http://www.springframework.org/schema/beans
                        http://www.springframework.org/schema/beans/spring-beans.xsd">

    <bean id="connectionFactory" class="org.springframework.jms.connection.CachingConnectionFactory">
        <property name="targetConnectionFactory">
            <bean class="org.apache.activemq.ActiveMQConnectionFactory">
                <property name="brokerURL" value="vm://localhost"/>
            </bean>
        </property>
    </bean>
        
    <bean id="postDestination" class="org.apache.activemq.command.ActiveMQQueue">
         <constructor-arg value="queue.post"/>
    </bean>
        
    <bean id="readDestination" class="org.apache.activemq.command.ActiveMQQueue">
         <constructor-arg value="queue.read"/>
    </bean>
        
    <bean id="followDestination" class="org.apache.activemq.command.ActiveMQQueue">
         <constructor-arg value="queue.follow"/>
    </bean>
        
    <bean id="wallDestination" class="org.apache.activemq.command.ActiveMQQueue">
         <constructor-arg value="queue.wall"/>
    </bean>
</beans>
